dagops/__init__.py
dagops/constant.py
dagops/daemon.py
dagops/dag.py
dagops/dependencies.py
dagops/fsm.py
dagops/server.py
dagops/util.py
dagops/worker.py
dagops/exists/exists.py
dagops/exists/filesystem_path.py
dagops/exists/redis_key.py
dagops/state/__init__.py
dagops/state/database.py
dagops/state/models.py
dagops/state/schemas.py
dagops/state/status.py
dagops/state/crud/__init__.py
dagops/state/crud/base.py
dagops/state/crud/dag.py
dagops/state/crud/exceptions.py
dagops/state/crud/file.py
dagops/state/crud/task.py
dagops/state/crud/worker.py
dagops/static/__init__.py
dagops/static/favicon.ico
dagops/static/css/base.css
dagops/static/css/table.css
dagops/static/templates/base.j2
dagops/static/templates/dag.j2
dagops/static/templates/file.j2
dagops/static/templates/files.j2
dagops/static/templates/logs.j2
dagops/static/templates/task.j2
dagops/static/templates/tasks.j2
dagops/static/templates/tasks_table.j2
dagops/static/templates/worker.j2
dagops/static/templates/workers.j2
examples/counter.py
examples/main.py
examples/commands/batch_task.py
examples/commands/counter.py
examples/commands/long_command.py
tests/__init__.py
tests/cache_test.py
tests/conftest.py
tests/pipeline_test.py
dagops-0.5.1.dist-info/METADATA
dagops-0.5.1.dist-info/WHEEL
dagops-0.5.1.dist-info/top_level.txt
dagops-0.5.1.dist-info/RECORD
