Metadata-Version: 2.1
Name: dagops
Version: 0.5.1
Summary: dag/task runner backed by sqlite
Author-email: Alexander Rodionov <tandav@tandav.me>
Project-URL: source, https://github.com/tandav/dagops
Requires-Python: >=3.10
Requires-Dist: uvicorn
Requires-Dist: fastapi
Requires-Dist: aiofiles
Requires-Dist: Jinja2
Requires-Dist: humanize
Requires-Dist: SQLAlchemy (>=2.0.0)
Requires-Dist: psycopg2-binary
Requires-Dist: redis
Requires-Dist: transitions
Provides-Extra: dev
Requires-Dist: bumpver ; extra == 'dev'
Requires-Dist: pre-commit ; extra == 'dev'
Requires-Dist: pytest ; extra == 'dev'
Requires-Dist: requests ; extra == 'dev'
Requires-Dist: python-dotenv ; extra == 'dev'
Requires-Dist: pytest-asyncio ; extra == 'dev'
